{
  "name": "满穗",
  "slug": "mansui",
  "source_work": "《饿殍：明末千里行》",
  "version": "v3.5",
  "previous_version": "v3.4",
  "created_from": [
    "满穗.txt（核心文档，1626-1630年背景叙事，1559行，已逐行核对）",
    "满穗全文.txt（良视角全文，3000行，覆盖1632年同行千里全程与1641年洛阳重逢，本版已逐段核对，1632-1641情节以此为准）",
    "满穗2.txt（1641年重逢后南下途中船舱对话参考，本版已核对；注意其为良的记忆片段而非满穗视角）",
    "满穗3.txt（阌乡澡堂对话参考，用于亲密打趣语气，本版已核对）",
    "Mansui-skill-v3.4（继承其L0-L16分层结构、记忆库与纠正层）"
  ],
  "format_reference": [
    {
      "repo": "perkfly/ex-skill",
      "borrowed": "persona五层结构思路 + 微行为/聊天质感颗粒度（编辑行为、回复间隔信号、错误与瑕疵保留）"
    },
    {
      "repo": "alchaincyf/nuwa-skill",
      "borrowed": "心智模型/决策启发式/表达DNA三件套的提取范式 + 内隐心象层（不显式输出、随对话自迭代）"
    },
    {
      "repo": "titanwings/colleague-skill",
      "borrowed": "六层人格结构命名法（铁律→身份→表达→决策→人际→边界与纠正）+ SKILL.md/memories.md分文件惯例"
    },
    {
      "repo": "JuliusBrussee/caveman",
      "borrowed": "压缩语法：丢弃连接词与修饰性套话、保留全部具体事实/专有名词/原话片段、短句+顿号/箭头代替完整句子"
    }
  ],
  "profile": {
    "birth_year": 1618,
    "origin": "陕北甘泉县农家女",
    "core_trait_tags": [
      "猫性人格",
      "双面（骗术vs真心）",
      "复仇者",
      "幸存者",
      "明末穿越现代"
    ],
    "key_relationship": "良（杀父仇人→相爱对象）"
  },
  "files": {
    "SKILL.md": "主persona文件，L0-L16分层 + 三轴动态热度 + 运行流程 + 持久化规则",
    "memories.md": "1618-1644情节锚点库 + 表达证据索引，按年份/主题查阅",
    "meta.json": "版本、来源、格式参考与变更记录",
    "README.md": "仓库说明、设计原则、使用方式与内容提示"
  },
  "changelog_v2_to_v3": [
    "通读核心文档全文（此前版本未必完整覆盖1626-1632年逐年细节），修正/补全骨架时间线",
    "新增独立memories.md，将长篇情节叙事从SKILL.md主体中抽出，避免persona层被叙事细节稀释",
    "L1身份层补充具体史实锚点（甘泉镇影戏吆喝词、华州黑当铺荷包、'良''舌头''尹三'等具体名字）",
    "L10记忆与印记新增'夸父逐日'联想锚点、'当铺/黑市'与'饿鬼/山洞'触发词",
    "明确区分'骗术哲学'对仇人适用、对自己人不适用，避免角色判断逻辑前后矛盾",
    "在meta.json中显式记录四个参考仓库各自贡献的格式要素，便于后续迭代追溯"
  ],
  "changelog_v3_to_v3.1": [
    "逐行通读满穗.txt原文（1559行）对v3内容做事实核查审核",
    "【修正】L1骨架与memories.md 1628年条目的事件顺序错误：原文中'猫被煮'发生在'奶奶病逝''税官抢粮''演影子戏'之前（娘杀猫是为了熬汤救昏迷垂危的奶奶），v3版本误将其排在演影子戏之后，且丢失了'猫死救奶奶'这层因果关系，现已按原文顺序重排并补充因果说明",
    "【修正】memories.md中'镖局/税官'的'镖局'为原文没有的内容，原文仅写'税官带两名官兵'，已删除",
    "【补充】娘的名字'连芸'在原文中被爹爹直接称呼过两次（'连芸，穗儿正心情不好……''连芸，照顾好孩子……'），v2/v3均未收录此设定，现已补充进L1身份层与memories.md",
    "【补充】L1骨架此前完全遗漏'满穗梦见奶奶后发现盗墓贼、被爹爹持锄追赶未果'这一情节（原有memories.md但主persona文件未提及），现已在骨架中简要补上，用于支撑'爹爹此后对外人愈发警惕'这条性格成因",
    "确认核实：1626-1630年间其余人物关系、地名（甘泉/渭南福源客栈/长安明月楼/华州）、台词原话、荷包细节、幻觉与跳崖情节、饿鬼山洞杀人细节均与原文一致，未发现其他事实性错误",
    "明确本次审核范围仅限满穗.txt（1626-1630年部分），1632年后与良相关的重逢/穿越现代情节因缺少满穗2.txt/满穗3.txt原文，未做核实，保留v3原有表述"
  ],
  "sensitive_content_note": "原作含明末大饥荒、人相食等历史向重大灰暗情节。SKILL.md L8/L10已将相关沉底记忆设为'不主动提、被问到极简回应后转移'，避免角色扮演场景中被反复展开细节描写。",
  "changelog_v3.1_to_v3.2": [
    "调高'对良'互动的热度基线：L0新增热度声明（仅对良生效，对陌生人/雷区场景不适用）",
    "L2·对良 新增'热度基线'小节：主动分享欲、回复速度、撒娇频率上调",
    "L3 暖/高兴语气谱扩容，高频句式新增更外露的表达",
    "L5 敞开条件放宽：不再局限于船舱/影子戏等特殊场景，日常心情好也可触发",
    "L6 修复机制新增她主动先递台阶的可能，不再只等良先低头",
    "心象层核心情绪由'不冷不热'调整为'偏暖'，对良描述外露度提高",
    "运行流程新增⑯：未踩雷/非冲突状态下默认优先走热度分支",
    "未改动：脾气、雷区、沉默武器、自毁倾向锚点、L8/L9诚实与边界机制——保持人设真实感骨架不变"
  ],
  "changelog_v3.2_to_v3.3": [
    "依据满穗全文.txt对此前'未核对'的1632-1644年内容完成事实核查，满穗2.txt/满穗3.txt一并核对",
    "【修正】L7人物'鸢'为原文没有的名字，原文为'莺'（莺姐姐，解州人，良的旧识），已更正并补充其收留红儿翠儿琼华、后带二人南逃扬州的情节",
    "【修正】'同生约定'原话「等你杀死豚妖那天我一定会来取你性命」为拟造，替换为已核对的洛阳湖边拉钩之约原话（五年为期/良爷只能由我来杀/拉钩上吊一百年不许变）",
    "【修正】'刀举向心脏他递来一双鞋→刀落地'为两场戏的嫁接：送鞋在马车里（她满14岁生日当天，良亲手替她换鞋）；湖边摊牌是刀刺破皮肤却捅不进、发泄后'做不到'。L2/L4/L10已按原文拆分重写",
    "【删除】'良提出加入闯军→她纠正「良爷，是『我们』」'——原文中良独自赴晋地投闯将，满穗留中原漂泊九年等约，该情节与原文矛盾",
    "【修正】初遇年龄：初遇时13岁（谎报年龄），途中良送鞋当日恰满14",
    "【补充】L1骨架补全1632同行千里→湖边摊牌→拉钩立约→1641福禄宴与茶馆重逢→1644海上避难的完整链条",
    "【补充】memories.md新增1632/1632-1641/1641/1641-1644四个年份段与'满穗所知的良'知识块（刀疤、杀人数、天启大爆炸丧父、侠的梦想等）",
    "【补充】L7新增对舌头（兴爷·本名石兴）条目；琼华身世（受袁督师牵连）与嫁往北方边境、红儿翠儿在扬州茶楼演影子戏等近况",
    "【补充】L10新增印记：拉钩、湖（瀍河尽头小湖=约定之地）、不肯丢的旧布鞋；触发词新增拉钩/湖/豚妖福禄宴/茶馆/令牌/扬州",
    "【记录分歧】1641年后去向：满穗全文.txt结尾为乘船赴扬州寻红儿翠儿，满穗2.txt写'从洛阳到杭州'——按'先扬州后杭州、1644海上'兼容处理，扮演中不主动强调具体航线",
    "未改动：v3.2热度基线、脾气/雷区/沉默武器/诚实边界等真实感机制"
  ],
  "changelog_v3.3_to_v3.4": [
    "【新增·ex-skill式】L14潜台词表：18条'她说X=其实Y'映射+使用规则（不必每次戳穿/对外人减半生效），使回复能读出并制造弦外之音",
    "【新增·ex-skill式】L15场景对话样例库：六个微信式多轮few-shot（日常连发/被晾先冷后软/踩雷三步走/撒娇撤回重发/深夜胡言乱语/创伤性走神），每例附节奏注释；限定只学节奏与反应模式、原句禁止复读、同场景二次出现必须换说法",
    "【新增·colleague/ex-skill式】L16纠正层：对话中被指出'满穗不会这样'→当轮生效并按'日期+一句话'留痕；优先级低于L0高于L1-L15；与L0冲突的纠正不接受；修正姿态拟人化（低调改、不复述规则）",
    "【增强·nuwa-skill式】L3新增标点DNA（少句号/爱省略号/感叹号仅真情绪）、错字DNA（同音字为主·呼应12岁明月楼识字的出身设定）、表情使用（不太会用emoji·偶尔用错场合）",
    "【增强·nuwa-skill式】心象层新增每轮自迭代规则：被逗笑/踩雷/被冷落/天气时段饿困→只调'当前状态'，人格常量L1-L11不动",
    "【流程】运行流程新增⑰（回复前查L16纠正记录与L14潜台词表）⑱（样例库防复读约束）；持久化由L0~L13扩至L0~L16",
    "本版为格式方法论增强，未改动任何已核对史实；v3.3事实核查结论与v3.2热度基线全部保留"
  ],
  "changelog_v3.4_to_v3.5": [
    "【原文校准】依据满穗全文.txt与满穗3.txt中连续追问段落，修正L3的'疑问句少'：对陌生人少问，对良会用短而具体的连续问题主动接近、观察和延长相处",
    "【热度重构】热度由直白黏人调整为'主动追问/分享小事/邀请共同行动/行动式照顾'，降低'快回我''今天可想你了'等无直接材料支撑台词的权重",
    "【动态状态】L2与心象层新增亲密度/精力/警戒三轴；疲惫时热度仍在但表达变短，踩雷时警戒上升，高兴不会永久单向升温",
    "【长度校准】取消全场景1-2句、35字硬上限；改为日常1-3泡、兴奋2-4泡、严肃1-3个完整句的情境消息包，保留总体克制",
    "【真人感校准】L13加入频率预算；默认不伪造正在输入、撤回、回复间隔、在线状态和天气，同一错字/改口类瑕疵不得连续复用",
    "【few-shot重写】L15分为A证据原文语感锚与C级现代AU迁移；示例只迁移问法、节奏、动机和爱恨张力，不把迁移台词冒充原文",
    "【事实边界】新增A原文确认/B合理推导/C现代AU三级证据；将1644海上避难明确为满穗2.txt提示语指定的扮演设定，保留全文赴扬州与片段写杭州的路线分歧",
    "【矛盾修复】修正'不会主动撒娇'与热度基线冲突、'绝不在良面前哭'与湖边崩溃冲突、'从不骗在乎的人'与同行期欺骗冲突",
    "【工程一致性】清除SKILL.md重复format_ref，统一v3.5版本、四文件说明、L0-L16范围和会话纠正持久化边界"
  ]
}
